type_fastapi/__init__.py
type_fastapi/commands/__init__.py
type_fastapi/commands/standard.py
type_fastapi/main.py
type_fastapi/utils.py
type_fastapi-0.1.7.dist-info/LICENSE
type_fastapi-0.1.7.dist-info/METADATA
type_fastapi-0.1.7.dist-info/WHEEL
type_fastapi-0.1.7.dist-info/entry_points.txt
type_fastapi-0.1.7.dist-info/RECORD
